{"cameraMode":{"drawMode":0,"name":"Shaded","section":"Shading Mode"},"sceneLighting":true,"audioPlay":false,"sceneViewState":{"m_AlwaysRefresh":false,"showFog":true,"showSkybox":true,"showFlares":true,"showImageEffects":true,"showParticleSystems":true,"showVisualEffectGraphs":true,"m_FxEnabled":true},"in2DMode":false,"pivot":{"x":7.204832077026367,"y":0.4020214080810547,"z":15.278508186340332},"rotation":{"x":-0.25328168272972109,"y":0.5173982977867127,"z":-0.1636340618133545,"w":-0.8008571267127991},"size":14.860950469970704,"orthographic":false}